serverside/__init__.py
serverside/generate_template.py
serverside/auth/__init__.py
serverside/auth/jwt.py
serverside/auth/passwords.py
serverside/aws/__init__.py
serverside/converters/__init__.py
serverside/converters/case.py
serverside/django/__init__.py
serverside/django/apps.py
serverside/django/fields.py
serverside/django/validators.py
serverside/dynamodb/__init__.py
serverside/dynamodb/jsonizer.py
serverside/generators/__init__.py
serverside/generators/identicon.py
serverside/graphql/__init__.py
serverside/graphql/ariadne/__init__.py
serverside/graphql/ariadne/base_resolver.py
serverside/graphql/ariadne/decorators.py
serverside/graphql/ariadne/extractors.py
serverside/graphql/ariadne/helpers.py
serverside/graphql/ariadne/relay.py
serverside/graphql/ariadne/scalars.py
serverside/graphql/ariadne/django_models/__init__.py
serverside/graphql/ariadne/django_models/_utils.py
serverside/graphql/ariadne/django_models/create.py
serverside/graphql/ariadne/django_models/delete.py
serverside/graphql/ariadne/django_models/get_many.py
serverside/graphql/ariadne/django_models/get_one.py
serverside/graphql/ariadne/django_models/update.py
serverside/gremlin/__init__.py
serverside/logging/__init__.py
serverside/middleware/__init__.py
serverside/redis/__init__.py
serverside/redis/client.py
serverside/redis/exceptions.py
serverside/server_side_events/__init__.py
serverside/testing/__init__.py
serverside-1.0.4.dist-info/METADATA
serverside-1.0.4.dist-info/WHEEL
serverside-1.0.4.dist-info/top_level.txt
serverside-1.0.4.dist-info/RECORD
