Metadata-Version: 2.1
Name: serverside
Version: 1.0.4
Summary: Python serverside toolkit
Home-page: https://github.com/asciialex/python-serverside
Author: asciialex
Author-email: alex@asciialex.com
License: UNKNOWN
Platform: UNKNOWN
Classifier: Programming Language :: Python :: 3
Classifier: License :: OSI Approved :: MIT License
Classifier: Operating System :: OS Independent
Requires-Python: >=3.6
